{
	"label": "Indigenous",
	"description": "Indigenous",
	"list": [{
			"label": "Creeland",
			"isbns": [
				"9780889713932"
			]
		},
		{
			"label": "Nature Poem",
			"isbns": [
				"9781941040645"
			]
		},
		{
			"label": "Perma Red",
			"isbns": [
				"9781639550647"
			]
		},
		{
			"label": "We Are the Middle of Forever",
			"isbns": [
				"9781620977194"
			]
		},
		{
			"label": "A Death in Bloomsbury",
			"isbns": [
				"9781916257368"
			]
		},
		{
			"label": "Something Fabulous",
			"isbns": [
				"9781542036290"
			]
		},
{
			"label": "Wild and Wicked Things",
			"isbns": [
				"9780316287159",
				"9780316287395"
			]
		},
{
			"label": "Delilah Green Doesn’t Care",
			"isbns": [
				"9780593336403",
				"9780593336410"
			]
		},
		{
			"label": "The Golden Season",
			"isbns": [
				"9781525899836"
			]
		},
		{
			"label": "Rainbow Rainbow",
			"isbns": [
				"99781646221011"
			]
		}
			
	]
}